{
  "entries": [
    {
      "item": "minecraft:dye|15",
      "emc": 0
    },
    {
      "item": "enderio:item_alloy_ingot|4",
      "emc": 0
    },
    {
      "item": "thermalfoundation:material|136",
      "emc": 0
    },
    {
      "item": "thermalfoundation:material|164",
      "emc": 0
    },
    {
      "item": "thermalfoundation:material|128",
      "emc": 0
    },
    {
      "item": "actuallyadditions:item_crystal|2",
      "emc": 0
    },
    {
      "item": "abyssalcraft:cingot|0",
      "emc": 0
    },
    {
      "item": "tconstruct:ingots|0",
      "emc": 0
    },
    {
      "item": "tconstruct:ingots|2",
      "emc": 0
    },
    {
      "item": "extrautils2:ingredients|5",
      "emc": 0
    },
    {
      "item": "mekanism:ingot|1",
      "emc": 0
    },
    {
      "item": "enderio:item_alloy_ingot|6",
      "emc": 0
    },
    {
      "item": "draconicevolution:nugget|1",
      "emc": 0
    },
    {
      "item": "extrautils2:ingredients|0",
      "emc": 0
    },
    {
      "item": "draconicevolution:draconic_ingot|0",
      "emc": 0
    },
    {
      "item": "nuclearcraft:ingot|7",
      "emc": 0
    },
    {
      "item": "botania:manaresource|0",
      "emc": 0
    },
    {
      "item": "thermalfoundation:material|133",
      "emc": 0
    },
    {
      "item": "minecraft:obsidian|0",
      "emc": 0
    },
    {
      "item": "extrautils2:ingredients|11",
      "emc": 0
    },
    {
      "item": "minecraft:prismarine_crystals|0",
      "emc": 0
    },
    {
      "item": "enderio:item_alloy_ingot|3",
      "emc": 0
    },
    {
      "item": "minecraft:egg|0",
      "emc": 0
    },
    {
      "item": "chickens:liquid_egg|1",
      "emc": 0
    },
    {
      "item": "minecraft:slime_ball|0",
      "emc": 0
    },
    {
      "item": "tconstruct:ingots|1",
      "emc": 0
    },
    {
      "item": "minecraft:flint|0",
      "emc": 0
    },
    {
      "item": "draconicevolution:draconium_ingot|0",
      "emc": 0
    },
    {
      "item": "thermalfoundation:material|162",
      "emc": 0
    },
    {
      "item": "minecraft:dye|0",
      "emc": 0
    },
    {
      "item": "minecraft:leather|0",
      "emc": 0
    },
    {
      "item": "minecraft:snowball|0",
      "emc": 0
    },
    {
      "item": "thermalfoundation:material|2052",
      "emc": 0
    },
    {
      "item": "minecraft:ghast_tear|0",
      "emc": 0
    },
    {
      "item": "abyssalcraft:dreadiumingot|0",
      "emc": 0
    },
    {
      "item": "thermalfoundation:material|199",
      "emc": 0
    },
    {
      "item": "thermalfoundation:material|135",
      "emc": 0
    },
    {
      "item": "minecraft:snow|0",
      "emc": 0
    },
    {
      "item": "minecraft:blaze_rod|0",
      "emc": 0
    },
    {
      "item": "minecraft:log|0",
      "emc": 0
    },
    {
      "item": "minecraft:string|0",
      "emc": 0
    },
    {
      "item": "actuallyadditions:item_misc|5",
      "emc": 0
    },
    {
      "item": "minecraft:glass|0",
      "emc": 0
    },
    {
      "item": "enderio:item_alloy_ingot|0",
      "emc": 0
    },
    {
      "item": "tconstruct:ingots|3",
      "emc": 0
    },
    {
      "item": "minecraft:stick|0",
      "emc": 0
    },
    {
      "item": "minecraft:planks|0",
      "emc": 0
    },
    {
      "item": "minecraft:dye|4",
      "emc": 0
    },
    {
      "item": "minecraft:magma_cream|0",
      "emc": 0
    },
    {
      "item": "chickens:liquid_egg|0",
      "emc": 0
    },
    {
      "item": "thermalfoundation:material|2050",
      "emc": 0
    },
    {
      "item": "minecraft:glowstone_dust|0",
      "emc": 0
    },
    {
      "item": "thermalfoundation:material|161",
      "emc": 0
    },
    {
      "item": "thermalfoundation:material|131",
      "emc": 0
    },
    {
      "item": "minecraft:magma|0",
      "emc": 0
    },
    {
      "item": "minecraft:clay_ball|0",
      "emc": 0
    },
    {
      "item": "minecraft:nether_wart|0",
      "emc": 0
    },
    {
      "item": "thermalfoundation:material|2048",
      "emc": 0
    },
    {
      "item": "minecraft:gold_ingot|0",
      "emc": 0
    },
    {
      "item": "botania:manaresource|7",
      "emc": 0
    },
    {
      "item": "nuclearcraft:ingot|6",
      "emc": 0
    },
    {
      "item": "minecraft:clay|0",
      "emc": 0
    },
    {
      "item": "minecraft:coal|0",
      "emc": 0
    },
    {
      "item": "minecraft:quartz|0",
      "emc": 0
    },
    {
      "item": "minecraft:dye|11",
      "emc": 0
    },
    {
      "item": "tconstruct:edible|3",
      "emc": 0
    },
    {
      "item": "minecraft:dye|2",
      "emc": 0
    },
    {
      "item": "actuallyadditions:item_crystal|4",
      "emc": 0
    },
    {
      "item": "thermalfoundation:material|166",
      "emc": 0
    },
    {
      "item": "minecraft:coal_block|0",
      "emc": 0
    },
    {
      "item": "minecraft:quartz_block|0",
      "emc": 0
    },
    {
      "item": "tconstruct:slime_congealed|0",
      "emc": 0
    },
    {
      "item": "minecraft:slime|0",
      "emc": 0
    },
    {
      "item": "minecraft:diamond|0",
      "emc": 0
    },
    {
      "item": "minecraft:dye|1",
      "emc": 0
    },
    {
      "item": "abyssalcraft:abyingot|0",
      "emc": 0
    },
    {
      "item": "tconstruct:edible|1",
      "emc": 0
    },
    {
      "item": "minecraft:gunpowder|0",
      "emc": 0
    },
    {
      "item": "thermalfoundation:material|231",
      "emc": 0
    },
    {
      "item": "extrautils2:ingredients|3",
      "emc": 0
    },
    {
      "item": "minecraft:diamond_block|0",
      "emc": 0
    },
    {
      "item": "abyssalcraft:ingotblock|0",
      "emc": 0
    },
    {
      "item": "minecraft:emerald|0",
      "emc": 0
    },
    {
      "item": "minecraft:redstone|0",
      "emc": 0
    },
    {
      "item": "thermalfoundation:material|132",
      "emc": 0
    },
    {
      "item": "nuclearcraft:ingot|5",
      "emc": 0
    },
    {
      "item": "minecraft:iron_ingot|0",
      "emc": 0
    },
    {
      "item": "enderio:item_alloy_ingot|1",
      "emc": 0
    },
    {
      "item": "extrautils2:decorativesolidwood|1",
      "emc": 0
    },
    {
      "item": "nuclearcraft:ingot_block|12",
      "emc": 0
    },
    {
      "item": "thermalfoundation:storage|4",
      "emc": 0
    },
    {
      "item": "minecraft:redstone_block|0",
      "emc": 0
    },
    {
      "item": "minecraft:emerald_block|0",
      "emc": 0
    },
    {
      "item": "minecraft:iron_block|0",
      "emc": 0
    },
    {
      "item": "minecraft:iron_bars|0",
      "emc": 0
    },
    {
      "item": "minecraft:iron_trapdoor|0",
      "emc": 0
    },
    {
      "item": "minecraft:iron_door|0",
      "emc": 0
    },
    {
      "item": "minecraft:iron_nugget|0",
      "emc": 0
    },
    {
      "item": "minecraft:ender_pearl|0",
      "emc": 0
    },
    {
      "item": "minecraft:sand|0",
      "emc": 0
    },
    {
      "item": "cyclicmagic:crystallized_amber|0",
      "emc": 0
    },
    {
      "item": "thermalfoundation:material|163",
      "emc": 0
    },
    {
      "item": "thermalfoundation:material|866",
      "emc": 0
    },
    {
      "item": "actuallyadditions:item_crystal|5",
      "emc": 0
    },
    {
      "item": "tconstruct:edible|4",
      "emc": 0
    },
    {
      "item": "actuallyadditions:block_misc|6",
      "emc": 0
    },
    {
      "item": "minecraft:soul_sand|0",
      "emc": 0
    },
    {
      "item": "enderio:item_alloy_ingot|7",
      "emc": 0
    },
    {
      "item": "minecraft:dye|7",
      "emc": 0
    },
    {
      "item": "minecraft:grass|0",
      "emc": 0
    },
    {
      "item": "minecraft:dirt|0",
      "emc": 0
    },
    {
      "item": "minecraft:dirt|1",
      "emc": 0
    },
    {
      "item": "minecraft:gravel|0",
      "emc": 0
    },
    {
      "item": "minecraft:cake|0",
      "emc": 0
    },
    {
      "item": "minecraft:dye|13",
      "emc": 0
    },
    {
      "item": "minecraft:dye|6",
      "emc": 0
    },
    {
      "item": "enderio:item_alloy_ingot|5",
      "emc": 0
    },
    {
      "item": "thermalfoundation:material|160",
      "emc": 0
    },
    {
      "item": "minecraft:dye|3",
      "emc": 0
    },
    {
      "item": "industrialforegoing:plastic|0",
      "emc": 0
    },
    {
      "item": "thermalfoundation:material|130",
      "emc": 0
    },
    {
      "item": "thermalfoundation:material|134",
      "emc": 0
    },
    {
      "item": "minecraft:dye|8",
      "emc": 0
    },
    {
      "item": "minecraft:dye|5",
      "emc": 0
    },
    {
      "item": "nuclearcraft:ingot|3",
      "emc": 0
    },
    {
      "item": "enderio:item_material|5",
      "emc": 0
    },
    {
      "item": "minecraft:dye|12",
      "emc": 0
    },
    {
      "item": "minecraft:dye|9",
      "emc": 0
    },
    {
      "item": "thermalfoundation:material|129",
      "emc": 0
    },
    {
      "item": "enderio:item_alloy_ingot|2",
      "emc": 0
    },
    {
      "item": "thermalfoundation:material|165",
      "emc": 0
    },
    {
      "item": "minecraft:prismarine_shard|0",
      "emc": 0
    },
    {
      "item": "minecraft:dye|14",
      "emc": 0
    },
    {
      "item": "nuclearcraft:ingot|4",
      "emc": 0
    },
    {
      "item": "minecraft:gold_block|0",
      "emc": 0
    },
    {
      "item": "abyssalcraft:ingotblock|1",
      "emc": 0
    },
    {
      "item": "abyssalcraft:ingotblock|2",
      "emc": 0
    },
    {
      "item": "actuallyadditions:block_misc|5",
      "emc": 0
    },
    {
      "item": "minecraft:nether_star|0",
      "emc": 0
    },
    {
      "item": "minecraft:netherbrick|0",
      "emc": 0
    },
    {
      "item": "appliedenergistics2:material|3",
      "emc": 0
    },
    {
      "item": "minecraft:nether_brick|0",
      "emc": 0
    },
    {
      "item": "tconstruct:metal|6",
      "emc": 0
    },
    {
      "item": "tconstruct:metal|2",
      "emc": 0
    },
    {
      "item": "tconstruct:metal|1",
      "emc": 0
    },
    {
      "item": "tconstruct:metal|0",
      "emc": 0
    },
    {
      "item": "thermalfoundation:storage_resource|0",
      "emc": 0
    },
    {
      "item": "thermalfoundation:storage_alloy|6",
      "emc": 0
    },
    {
      "item": "thermalfoundation:storage_alloy|5",
      "emc": 0
    },
    {
      "item": "thermalfoundation:storage_alloy|3",
      "emc": 0
    },
    {
      "item": "thermalfoundation:storage_alloy|2",
      "emc": 0
    },
    {
      "item": "thermalfoundation:storage|0",
      "emc": 0
    },
    {
      "item": "thermalfoundation:storage_alloy|1",
      "emc": 0
    },
    {
      "item": "thermalfoundation:storage_alloy|0",
      "emc": 0
    },
    {
      "item": "thermalfoundation:storage|6",
      "emc": 0
    },
    {
      "item": "thermalfoundation:storage|5",
      "emc": 0
    },
    {
      "item": "thermalfoundation:storage|3",
      "emc": 0
    },
    {
      "item": "thermalfoundation:storage|2",
      "emc": 0
    },
    {
      "item": "thermalfoundation:storage|1",
      "emc": 0
    },
    {
      "item": "nuclearcraft:ingot_block|13",
      "emc": 0
    },
    {
      "item": "nuclearcraft:ingot_block|1",
      "emc": 0
    },
    {
      "item": "nuclearcraft:ingot_block|2",
      "emc": 0
    },
    {
      "item": "nuclearcraft:ingot_block|3",
      "emc": 0
    },
    {
      "item": "nuclearcraft:ingot_block|4",
      "emc": 0
    },
    {
      "item": "nuclearcraft:ingot_block|5",
      "emc": 0
    },
    {
      "item": "nuclearcraft:ingot_block|6",
      "emc": 0
    },
    {
      "item": "nuclearcraft:ingot_block|7",
      "emc": 0
    },
    {
      "item": "nuclearcraft:ingot_block|8",
      "emc": 0
    },
    {
      "item": "nuclearcraft:ingot|8",
      "emc": 0
    },
    {
      "item": "mekanism:ingot|6",
      "emc": 0
    },
    {
      "item": "mekanism:ingot|5",
      "emc": 0
    },
    {
      "item": "mekanism:ingot|4",
      "emc": 0
    },
    {
      "item": "mekanism:ingot|2",
      "emc": 0
    },
    {
      "item": "nuclearcraft:ingot|0",
      "emc": 0
    },
    {
      "item": "nuclearcraft:ingot|1",
      "emc": 0
    },
    {
      "item": "nuclearcraft:ingot|2",
      "emc": 0
    },
    {
      "item": "nuclearcraft:ingot|12",
      "emc": 0
    },
    {
      "item": "nuclearcraft:ingot|13",
      "emc": 0
    },
    {
      "item": "nuclearcraft:alloy|0",
      "emc": 0
    },
    {
      "item": "nuclearcraft:alloy|5",
      "emc": 0
    },
    {
      "item": "nuclearcraft:ingot_block|0",
      "emc": 0
    },
    {
      "item": "appliedenergistics2:material|2",
      "emc": 0
    },
    {
      "item": "appliedenergistics2:material|8",
      "emc": 0
    },
    {
      "item": "appliedenergistics2:material|51",
      "emc": 0
    },
    {
      "item": "appliedenergistics2:material|49",
      "emc": 0
    },
    {
      "item": "mekanism:dust|0",
      "emc": 0
    },
    {
      "item": "mekanism:dust|1",
      "emc": 0
    },
    {
      "item": "mekanism:dust|3",
      "emc": 0
    },
    {
      "item": "mekanism:dust|4",
      "emc": 0
    },
    {
      "item": "mekanism:dust|5",
      "emc": 0
    },
    {
      "item": "nuclearcraft:dust|12",
      "emc": 0
    },
    {
      "item": "nuclearcraft:dust|8",
      "emc": 0
    },
    {
      "item": "nuclearcraft:dust|7",
      "emc": 0
    },
    {
      "item": "nuclearcraft:dust|6",
      "emc": 0
    },
    {
      "item": "nuclearcraft:dust|0",
      "emc": 0
    },
    {
      "item": "nuclearcraft:dust|1",
      "emc": 0
    },
    {
      "item": "nuclearcraft:dust|5",
      "emc": 0
    },
    {
      "item": "mekanism:dust|6",
      "emc": 0
    },
    {
      "item": "mekanism:otherdust|0",
      "emc": 0
    },
    {
      "item": "mekanism:otherdust|1",
      "emc": 0
    },
    {
      "item": "mekanism:otherdust|3",
      "emc": 0
    },
    {
      "item": "mekanism:otherdust|4",
      "emc": 0
    },
    {
      "item": "mekanism:otherdust|6",
      "emc": 0
    },
    {
      "item": "nuclearcraft:dust|4",
      "emc": 0
    },
    {
      "item": "nuclearcraft:dust|3",
      "emc": 0
    },
    {
      "item": "nuclearcraft:dust|2",
      "emc": 0
    },
    {
      "item": "minecraft:stone|0",
      "emc": 0
    },
    {
      "item": "minecraft:cobblestone|0",
      "emc": 0
    },
    {
      "item": "minecraft:stonebrick|0",
      "emc": 0
    },
    {
      "item": "minecraft:stonebrick|1",
      "emc": 0
    },
    {
      "item": "minecraft:stonebrick|2",
      "emc": 0
    },
    {
      "item": "minecraft:stonebrick|3",
      "emc": 0
    },
    {
      "item": "minecraft:red_sandstone|0",
      "emc": 0
    },
    {
      "item": "minecraft:red_sandstone|1",
      "emc": 0
    },
    {
      "item": "minecraft:red_sandstone|2",
      "emc": 0
    },
    {
      "item": "minecraft:red_sandstone_stairs|0",
      "emc": 0
    },
    {
      "item": "minecraft:stone_slab2|0",
      "emc": 0
    },
    {
      "item": "minecraft:end_bricks|0",
      "emc": 0
    },
    {
      "item": "minecraft:mossy_cobblestone|0",
      "emc": 0
    },
    {
      "item": "thermalfoundation:material|769",
      "emc": 0
    },
    {
      "item": "thermalfoundation:material|768",
      "emc": 0
    },
    {
      "item": "thermalfoundation:material|0",
      "emc": 0
    },
    {
      "item": "thermalfoundation:material|1",
      "emc": 0
    },
    {
      "item": "thermalfoundation:material|64",
      "emc": 0
    },
    {
      "item": "thermalfoundation:material|65",
      "emc": 0
    },
    {
      "item": "thermalfoundation:material|66",
      "emc": 0
    },
    {
      "item": "thermalfoundation:material|67",
      "emc": 0
    },
    {
      "item": "thermalfoundation:material|68",
      "emc": 0
    },
    {
      "item": "thermalfoundation:material|770",
      "emc": 0
    },
    {
      "item": "minecraft:planks|1",
      "emc": 0
    },
    {
      "item": "minecraft:planks|2",
      "emc": 0
    },
    {
      "item": "minecraft:planks|3",
      "emc": 0
    },
    {
      "item": "minecraft:planks|4",
      "emc": 0
    },
    {
      "item": "minecraft:planks|5",
      "emc": 0
    },
    {
      "item": "minecraft:log|1",
      "emc": 0
    },
    {
      "item": "minecraft:log|2",
      "emc": 0
    },
    {
      "item": "minecraft:log|3",
      "emc": 0
    },
    {
      "item": "minecraft:wooden_slab|1",
      "emc": 0
    },
    {
      "item": "minecraft:wooden_slab|2",
      "emc": 0
    },
    {
      "item": "minecraft:wooden_slab|3",
      "emc": 0
    },
    {
      "item": "minecraft:wooden_slab|4",
      "emc": 0
    },
    {
      "item": "minecraft:wooden_slab|5",
      "emc": 0
    },
    {
      "item": "minecraft:spruce_stairs|0",
      "emc": 0
    },
    {
      "item": "minecraft:birch_stairs|0",
      "emc": 0
    },
    {
      "item": "minecraft:jungle_stairs|0",
      "emc": 0
    },
    {
      "item": "minecraft:log2|0",
      "emc": 0
    },
    {
      "item": "minecraft:log2|1",
      "emc": 0
    },
    {
      "item": "minecraft:acacia_stairs|0",
      "emc": 0
    },
    {
      "item": "minecraft:dark_oak_stairs|0",
      "emc": 0
    },
    {
      "item": "abyssalcraft:dltplank|0",
      "emc": 0
    },
    {
      "item": "abyssalcraft:dltstairs|0",
      "emc": 0
    },
    {
      "item": "abyssalcraft:dltslab1|0",
      "emc": 0
    },
    {
      "item": "abyssalcraft:dltfence|0",
      "emc": 0
    },
    {
      "item": "minecraft:spruce_door|0",
      "emc": 0
    },
    {
      "item": "minecraft:birch_door|0",
      "emc": 0
    },
    {
      "item": "minecraft:jungle_door|0",
      "emc": 0
    },
    {
      "item": "minecraft:acacia_door|0",
      "emc": 0
    },
    {
      "item": "minecraft:dark_oak_door|0",
      "emc": 0
    },
    {
      "item": "quark:spruce_trapdoor|0",
      "emc": 0
    },
    {
      "item": "quark:birch_trapdoor|0",
      "emc": 0
    },
    {
      "item": "quark:jungle_trapdoor|0",
      "emc": 0
    },
    {
      "item": "quark:acacia_trapdoor|0",
      "emc": 0
    },
    {
      "item": "quark:dark_oak_trapdoor|0",
      "emc": 0
    },
    {
      "item": "quark:stained_planks|0",
      "emc": 0
    },
    {
      "item": "quark:stained_planks|1",
      "emc": 0
    },
    {
      "item": "quark:stained_planks|2",
      "emc": 0
    },
    {
      "item": "quark:stained_planks|4",
      "emc": 0
    },
    {
      "item": "quark:stained_planks|3",
      "emc": 0
    },
    {
      "item": "quark:stained_planks|5",
      "emc": 0
    },
    {
      "item": "quark:stained_planks|6",
      "emc": 0
    },
    {
      "item": "quark:stained_planks|7",
      "emc": 0
    },
    {
      "item": "quark:stained_planks|8",
      "emc": 0
    },
    {
      "item": "quark:stained_planks|15",
      "emc": 0
    },
    {
      "item": "quark:stained_planks|14",
      "emc": 0
    },
    {
      "item": "quark:stained_planks|13",
      "emc": 0
    },
    {
      "item": "quark:stained_planks|12",
      "emc": 0
    },
    {
      "item": "quark:stained_planks|11",
      "emc": 0
    },
    {
      "item": "quark:stained_planks|10",
      "emc": 0
    },
    {
      "item": "quark:stained_planks|9",
      "emc": 0
    },
    {
      "item": "quark:vertical_planks|0",
      "emc": 0
    },
    {
      "item": "quark:vertical_planks|1",
      "emc": 0
    },
    {
      "item": "quark:vertical_planks|2",
      "emc": 0
    },
    {
      "item": "quark:vertical_planks|3",
      "emc": 0
    },
    {
      "item": "quark:vertical_planks|4",
      "emc": 0
    },
    {
      "item": "quark:vertical_planks|5",
      "emc": 0
    },
    {
      "item": "quark:vertical_stained_planks|0",
      "emc": 0
    },
    {
      "item": "quark:vertical_stained_planks|1",
      "emc": 0
    },
    {
      "item": "quark:vertical_stained_planks|2",
      "emc": 0
    },
    {
      "item": "quark:vertical_stained_planks|3",
      "emc": 0
    },
    {
      "item": "quark:vertical_stained_planks|4",
      "emc": 0
    },
    {
      "item": "quark:vertical_stained_planks|5",
      "emc": 0
    },
    {
      "item": "quark:vertical_stained_planks|6",
      "emc": 0
    },
    {
      "item": "quark:vertical_stained_planks|7",
      "emc": 0
    },
    {
      "item": "quark:vertical_stained_planks|8",
      "emc": 0
    },
    {
      "item": "quark:vertical_stained_planks|9",
      "emc": 0
    },
    {
      "item": "quark:vertical_stained_planks|10",
      "emc": 0
    },
    {
      "item": "quark:vertical_stained_planks|11",
      "emc": 0
    },
    {
      "item": "quark:vertical_stained_planks|15",
      "emc": 0
    },
    {
      "item": "quark:vertical_stained_planks|14",
      "emc": 0
    },
    {
      "item": "quark:vertical_stained_planks|13",
      "emc": 0
    },
    {
      "item": "quark:vertical_stained_planks|12",
      "emc": 0
    },
    {
      "item": "quark:stained_planks_white_stairs|0",
      "emc": 0
    },
    {
      "item": "quark:stained_planks_orange_stairs|0",
      "emc": 0
    },
    {
      "item": "quark:stained_planks_magenta_stairs|0",
      "emc": 0
    },
    {
      "item": "quark:stained_planks_light_blue_stairs|0",
      "emc": 0
    },
    {
      "item": "quark:stained_planks_yellow_stairs|0",
      "emc": 0
    },
    {
      "item": "quark:stained_planks_lime_stairs|0",
      "emc": 0
    },
    {
      "item": "quark:stained_planks_pink_stairs|0",
      "emc": 0
    },
    {
      "item": "quark:stained_planks_gray_stairs|0",
      "emc": 0
    },
    {
      "item": "quark:stained_planks_silver_stairs|0",
      "emc": 0
    },
    {
      "item": "quark:stained_planks_black_stairs|0",
      "emc": 0
    },
    {
      "item": "quark:stained_planks_red_stairs|0",
      "emc": 0
    },
    {
      "item": "quark:stained_planks_green_stairs|0",
      "emc": 0
    },
    {
      "item": "quark:stained_planks_brown_stairs|0",
      "emc": 0
    },
    {
      "item": "quark:stained_planks_blue_stairs|0",
      "emc": 0
    },
    {
      "item": "quark:stained_planks_purple_stairs|0",
      "emc": 0
    },
    {
      "item": "quark:stained_planks_cyan_stairs|0",
      "emc": 0
    },
    {
      "item": "quark:bark_oak_stairs|0",
      "emc": 0
    },
    {
      "item": "quark:bark_spruce_stairs|0",
      "emc": 0
    },
    {
      "item": "quark:bark_birch_stairs|0",
      "emc": 0
    },
    {
      "item": "quark:bark_jungle_stairs|0",
      "emc": 0
    },
    {
      "item": "quark:bark_acacia_stairs|0",
      "emc": 0
    },
    {
      "item": "quark:bark_dark_oak_stairs|0",
      "emc": 0
    },
    {
      "item": "quark:stone_granite_stairs|0",
      "emc": 0
    },
    {
      "item": "quark:stone_diorite_stairs|0",
      "emc": 0
    },
    {
      "item": "quark:stone_andesite_stairs|0",
      "emc": 0
    },
    {
      "item": "quark:turf_stairs|0",
      "emc": 0
    },
    {
      "item": "quark:reed_block_stairs|0",
      "emc": 0
    },
    {
      "item": "quark:stone_andesite_bricks_stairs|0",
      "emc": 0
    },
    {
      "item": "quark:stone_diorite_bricks_stairs|0",
      "emc": 0
    },
    {
      "item": "quark:stone_granite_bricks_stairs|0",
      "emc": 0
    },
    {
      "item": "quark:stonebrick_mossy_stairs|0",
      "emc": 0
    },
    {
      "item": "quark:cobblestone_mossy_stairs|0",
      "emc": 0
    },
    {
      "item": "quark:bark|2",
      "emc": 0
    },
    {
      "item": "quark:bark|1",
      "emc": 0
    },
    {
      "item": "quark:bark|3",
      "emc": 0
    },
    {
      "item": "quark:bark|4",
      "emc": 0
    },
    {
      "item": "quark:bark|5",
      "emc": 0
    },
    {
      "item": "minecraft:wheat|0",
      "emc": 0
    },
    {
      "item": "minecraft:beetroot|0",
      "emc": 0
    },
    {
      "item": "minecraft:beetroot_seeds|0",
      "emc": 0
    },
    {
      "item": "minecraft:wheat_seeds|0",
      "emc": 0
    },
    {
      "item": "minecraft:pumpkin_seeds|0",
      "emc": 0
    },
    {
      "item": "minecraft:melon_seeds|0",
      "emc": 0
    },
    {
      "item": "minecraft:pumpkin|0",
      "emc": 0
    },
    {
      "item": "minecraft:melon_block|0",
      "emc": 0
    },
    {
      "item": "minecraft:melon|0",
      "emc": 0
    },
    {
      "item": "minecraft:cactus|0",
      "emc": 0
    },
    {
      "item": "minecraft:sugar|0",
      "emc": 0
    },
    {
      "item": "minecraft:reeds|0",
      "emc": 0
    },
    {
      "item": "quark:reed_block|0",
      "emc": 0
    },
    {
      "item": "quark:reed_block_slab|0",
      "emc": 0
    },
    {
      "item": "quark:reed_block_wall|0",
      "emc": 0
    }
  ]
}